marys/__init__.py
marys-1.1.1.dist-info/METADATA
marys-1.1.1.dist-info/WHEEL
marys-1.1.1.dist-info/licence
marys-1.1.1.dist-info/top_level.txt
marys-1.1.1.dist-info/RECORD
