Metadata-Version: 2.1
Name: marys
Version: 1.1.1
Summary: Library to obtain dining hours and menus at Swarthmore College
Home-page: https://github.com/codeofdusk/marys
Author: Bill Dengler
Author-email: codeofdusk@gmail.com
Classifier: Programming Language :: Python :: 3
Classifier: License :: OSI Approved :: Apache Software License
Classifier: Operating System :: OS Independent
Requires-Python: >=3.6
License-File: licence
Requires-Dist: requests
Requires-Dist: aiohttp
Requires-Dist: pytz
Requires-Dist: python-dateutil
Requires-Dist: unidecode
